[
  {
    "question": "Hvilken er GTA 2?",
    "alternatives": [
      {
        "text": "",
        "media": "gta3",
        "type": "img",
        "solution": false
      },{
        "text": "",
        "media": "gta2",
        "type": "img",
        "solution": true
      },{
        "text": "",
        "media": "carmageddon",
        "type": "img",
        "solution": false
      },{
        "text": "",
        "media": "batman",
        "type": "img",
        "solution": false
      }
    ]
  },
  {
    "question": "Hvilken er fra Tekken?",
    "alternatives": [
      {
        "text": "",
        "media": "tekken",
        "type": "img",
        "solution": true
      },{
        "text": "",
        "media": "streetfigther2",
        "type": "img",
        "solution": false
      },{
        "text": "",
        "media": "marvel",
        "type": "img",
        "solution": false
      },{
        "text": "",
        "media": "lechuck",
        "type": "img",
        "solution": false
      }
    ]
  },
  {
    "question": "Hvem er fra Rayman 1?",
    "alternatives": [
      {
        "text": "",
        "media": "contra3",
        "type": "img",
        "solution": false
      },{
        "text": "",
        "media": "rayman1",
        "type": "img",
        "solution": true
      },{
        "text": "",
        "media": "rayman3",
        "type": "img",
        "solution": false
      },{
        "text": "",
        "media": "ravinrabbids",
        "type": "img",
        "solution": false
      }
    ]
  },
  {
    "question": "Hvem er Jak And Daxter?",
    "alternatives": [
      {
        "text": "",
        "media": "darksouls2",
        "type": "img",
        "solution": false
      },{
        "text": "",
        "media": "jakanddaxter",
        "type": "img",
        "solution": true
      },{
        "text": "",
        "media": "thelostvikings",
        "type": "img",
        "solution": false
      },{
        "text": "",
        "media": "gearsofwar",
        "type": "img",
        "solution": false
      }
    ]
  },
  {
    "question": "Hvem er fra Bioshock?",
    "alternatives": [
      {
        "text": "",
        "media": "gta3",
        "type": "img",
        "solution": false
      },{
        "text": "",
        "media": "donaldduck",
        "type": "img",
        "solution": false
      },{
        "text": "",
        "media": "bioshock",
        "type": "img",
        "solution": true
      },{
        "text": "",
        "media": "battlefield4",
        "type": "img",
        "solution": false
      }
    ]
  },
  {
    "question": "Hvem er Kratos?",
    "alternatives": [
      {
        "text": "",
        "media": "kratos",
        "type": "img",
        "solution": true
      },{
        "text": "",
        "media": "zombie",
        "type": "img",
        "solution": false
      },{
        "text": "",
        "media": "destiny",
        "type": "img",
        "solution": false
      },{
        "text": "",
        "media": "tonyhawklosgatos",
        "type": "img",
        "solution": false
      }
    ]
  },
  {
    "question": "Hvem er fra GTA 2?",
    "alternatives": [
      {
        "text": "",
        "media": "gta3",
        "type": "img",
        "solution": false
      },{
        "text": "",
        "media": "gta2",
        "type": "img",
        "solution": true
      },{
        "text": "",
        "media": "carmageddon",
        "type": "img",
        "solution": false
      },{
        "text": "",
        "media": "batman",
        "type": "img",
        "solution": false
      }
    ]
  },
  {
    "question": "Hvilken er den første playstation-1 kontrolleren?",
    "alternatives": [
      {
        "text": "",
        "media": "psvita",
        "type": "img",
        "solution": false
      },{
        "text": "",
        "media": "ps1controll2",
        "type": "img",
        "solution": false
      },{
        "text": "",
        "media": "ps1controller",
        "type": "img",
        "solution": true
      },{
        "text": "",
        "media": "playstation4",
        "type": "img",
        "solution": false
      }
    ]
  },
  {
    "question": "Hvilken playstation er nyest?",
    "alternatives": [
      {
        "text": "",
        "media": "playstation3",
        "type": "img",
        "solution": false
      },{
        "text": "",
        "media": "playstation4",
        "type": "img",
        "solution": true
      },{
        "text": "",
        "media": "psvita",
        "type": "img",
        "solution": false
      },{
        "text": "",
        "media": "playstation2",
        "type": "img",
        "solution": false
      }
    ]
  },
  {
    "question": "Hvilken er singstar?",
    "alternatives": [
      {
        "text": "",
        "media": "gta3",
        "type": "img",
        "solution": false
      },{
        "text": "",
        "media": "rockband",
        "type": "img",
        "solution": false
      },{
        "text": "",
        "media": "guitarhero2",
        "type": "img",
        "solution": false
      },{
        "text": "",
        "media": "singstar",
        "type": "img",
        "solution": true
      }
    ]
  },
  {
    "question": "Hvilken er fra Rockband?",
    "alternatives": [
      {
        "text": "",
        "media": "gta3",
        "type": "img",
        "solution": false
      },{
        "text": "",
        "media": "rockband",
        "type": "img",
        "solution": true
      },{
        "text": "",
        "media": "guitarhero2",
        "type": "img",
        "solution": false
      },{
        "text": "",
        "media": "singstar",
        "type": "img",
        "solution": false
      }
    ]
  },
  {
    "question": "Hvilket er resident evil 2?",
    "alternatives": [
      {
        "text": "",
        "media": "ninjagaiden",
        "type": "img",
        "solution": false
      },{
        "text": "",
        "media": "masterchief",
        "type": "img",
        "solution": false
      },{
        "text": "",
        "media": "residentevil2",
        "type": "img",
        "solution": true
      },{
        "text": "",
        "media": "ridgeracer",
        "type": "img",
        "solution": false
      }
    ]
  },
  {
    "question": "Hvilken er fra Ridge Racer?",
    "alternatives": [
      {
        "text": "",
        "media": "needforspeed2",
        "type": "img",
        "solution": false
      },{
        "text": "",
        "media": "gta2",
        "type": "img",
        "solution": true
      },{
        "text": "",
        "media": "carmageddon",
        "type": "img",
        "solution": false
      },{
        "text": "",
        "media": "ridgeracer",
        "type": "img",
        "solution": true
      }
    ]
  },
  {
    "question": "Hvilken er fra Wipeout?",
    "alternatives": [
      {
        "text": "",
        "media": "gta3",
        "type": "img",
        "solution": false
      },{
        "text": "",
        "media": "gta2",
        "type": "img",
        "solution": false
      },{
        "text": "",
        "media": "wipeout",
        "type": "img",
        "solution": true
      },{
        "text": "",
        "media": "batman",
        "type": "img",
        "solution": false
      }
    ]
  },
  {
    "question": "Hvem er spyro?",
    "alternatives": [
      {
        "text": "",
        "media": "spyro",
        "type": "img",
        "solution": true
      },{
        "text": "",
        "media": "mario",
        "type": "img",
        "solution": false
      },{
        "text": "",
        "media": "pikachu",
        "type": "img",
        "solution": false
      },{
        "text": "",
        "media": "charmander",
        "type": "img",
        "solution": false
      }
    ]
  },
  {
    "question": "Hvem er Crash Bandicoot?",
    "alternatives": [
      {
        "text": "",
        "media": "wipeout",
        "type": "img",
        "solution": false
      },{
        "text": "",
        "media": "jakanddaxter",
        "type": "img",
        "solution": false
      },{
        "text": "",
        "media": "crashbandicoot",
        "type": "img",
        "solution": true
      },{
        "text": "",
        "media": "kratos",
        "type": "img",
        "solution": false
      }
    ]
  },
  {
    "question": "Hvem er fra Tony Hawk?",
    "alternatives": [
      {
        "text": "",
        "media": "skate3",
        "type": "img",
        "solution": false
      },{
        "text": "",
        "media": "tonyhawk",
        "type": "img",
        "solution": true
      },{
        "text": "",
        "media": "squirtlecharmanderbulbasaur",
        "type": "img",
        "solution": false
      },{
        "text": "",
        "media": "subsero",
        "type": "img",
        "solution": false
      }
    ]
  },
  {
    "question": "Hvilket er et horrorspill?",
    "alternatives": [
      {
        "text": "",
        "media": "silenthill",
        "type": "img",
        "solution": true
      },{
        "text": "",
        "media": "thelongestjourney",
        "type": "img",
        "solution": false
      },{
        "text": "",
        "media": "wowdude",
        "type": "img",
        "solution": false
      },{
        "text": "",
        "media": "turtlesintime",
        "type": "img",
        "solution": false
      }
    ]
  },
  {
    "question": "Hvilket er fra Castlevania IV?",
    "alternatives": [
      {
        "text": "",
        "media": "thelongestjourney",
        "type": "img",
        "solution": false
      },{
        "text": "",
        "media": "wowdude",
        "type": "img",
        "solution": true
      },{
        "text": "",
        "media": "silenthill",
        "type": "img",
        "solution": false
      },{
        "text": "",
        "media": "castlevaniaIV",
        "type": "img",
        "solution": true
      }
    ]
  }
]